MANIFEST.in
info.py
setup.py
version.py
lib/rita/__init__.py
lib/rita/controller.py
lib/rita/field.py
lib/rita/session.py
lib/rita/test.py
lib/rita/validator.py
lib/rita.egg-info/PKG-INFO
lib/rita.egg-info/SOURCES.txt
lib/rita.egg-info/dependency_links.txt
lib/rita.egg-info/top_level.txt
lib/rita/misc/__init__.py
lib/rita/misc/facade.py
lib/rita/misc/controller/restapibasecontroller.py
lib/rita/misc/session/__init__.py
lib/rita/misc/session/dbmsessionstore.py
lib/rita/misc/session/pyhssessionstore.py