Metadata-Version: 1.1
Name: rita
Version: 0.0.2
Summary: Python Web Application Framework
Home-page: https://bitbucket.com/urushio
Author: Takayoshi Urushio
Author-email: uru@craft-works.jp
License: MIT License
Platform: UNKNOWN
Classifier: Programming Language :: Python :: 2.7
Classifier: Programming Language :: Python :: 3.3
Classifier: License :: OSI Approved :: MIT License
